rms_tabulation-2.0.0.dist-info/licenses/LICENSE
tabulation/__init__.py
tabulation/_version.py
rms_tabulation-2.0.0.dist-info/METADATA
rms_tabulation-2.0.0.dist-info/WHEEL
rms_tabulation-2.0.0.dist-info/top_level.txt
rms_tabulation-2.0.0.dist-info/RECORD
