Metadata-Version: 2.4
Name: rms-tabulation
Version: 2.0.0
Summary: A class that performs linear interpolation
Maintainer-email: "Robert S. French" <rfrench@seti.org>
License: Apache-2.0
Project-URL: Homepage, https://github.com/SETI/rms-tabulation
Project-URL: Documentation, https://rms-tabulation.readthedocs.io/en/latest
Project-URL: Repository, https://github.com/SETI/rms-tabulation
Project-URL: Source, https://github.com/SETI/rms-tabulation
Project-URL: Issues, https://github.com/SETI/rms-tabulation/issues
Keywords: interpolation
Classifier: Development Status :: 5 - Production/Stable
Classifier: Natural Language :: English
Classifier: Topic :: Scientific/Engineering
Classifier: Topic :: Scientific/Engineering :: Mathematics
Classifier: Topic :: Software Development :: Libraries :: Python Modules
Classifier: Topic :: Utilities
Classifier: License :: OSI Approved :: Apache Software License
Classifier: Programming Language :: Python :: 3.8
Classifier: Programming Language :: Python :: 3.9
Classifier: Programming Language :: Python :: 3.10
Classifier: Programming Language :: Python :: 3.11
Classifier: Programming Language :: Python :: 3.12
Classifier: Programming Language :: Python :: 3.13
Classifier: Operating System :: MacOS :: MacOS X
Classifier: Operating System :: POSIX :: Linux
Classifier: Operating System :: Microsoft :: Windows
Requires-Python: >=3.8
License-File: LICENSE
Requires-Dist: numpy
Requires-Dist: scipy
Dynamic: license-file
